google/__init__.py
google/__main__.py
google/__version__.py
google/googlecmd.py
googlecmd-0.1.0.dist-info/LICENSE
googlecmd-0.1.0.dist-info/METADATA
googlecmd-0.1.0.dist-info/WHEEL
googlecmd-0.1.0.dist-info/entry_points.txt
googlecmd-0.1.0.dist-info/top_level.txt
googlecmd-0.1.0.dist-info/RECORD
