Metadata-Version: 2.1
Name: googlecmd
Version: 0.1.0
Summary: Launch google search query from the command line.
Author-email: alexpdev <alexpdev@pm.me>
Project-URL: homepage, https://github.com/alexpdev/googlecmd
Project-URL: repository, https://github.com
Project-URL: documentation, https://alexpdev.github.io/googlecmd
Project-URL: changelog, https://alexpdev.github.io/googlecmd/changelog/
Project-URL: issues, https://github.com/alexpdev/googlecmd/issues
Keywords: Google-Search,Search-Engine,Query,Browser,CLI
Classifier: Environment :: Console
Classifier: Development Status :: 4 - Beta
Classifier: Operating System :: OS Independent
Classifier: Programming Language :: Python
Classifier: Programming Language :: Python :: 3
Classifier: Programming Language :: Python :: 3.6
Classifier: Programming Language :: Python :: 3.7
Classifier: Programming Language :: Python :: 3.8
Classifier: Programming Language :: Python :: 3.9
Classifier: Programming Language :: Python :: 3.10
Classifier: Programming Language :: Python :: 3.11
Classifier: Programming Language :: Python :: 3 :: Only
Classifier: Intended Audience :: End Users/Desktop
Classifier: Intended Audience :: Developers
Classifier: Topic :: Utilities
Classifier: License :: OSI Approved :: Apache Software License
Requires-Python: >=3.6
License-File: LICENSE
